{
  "Players": [
    {
      "Id": 1,
      "IsComputer": false,
      "Squads": [
        {
          "Units": [
            {
              "Id": 1,
              "Name": null,
              "UnitTypeId": "G000UU8020", // шершень.
              "SquadLinePosition": 0,
              "SquadFlankPosition": 2,
              "Level": 3,
              "Experience": 0,
              "HitPoints": 125,
              "IsDead": false
            },
            {
              "Id": 2,
              "Name": null,
              "UnitTypeId": "G000UU8024", // часовой.
              "SquadLinePosition": 0,
              "SquadFlankPosition": 1,
              "Level": 3,
              "Experience": 0,
              "HitPoints": 120,
              "IsDead": false
            },
            {
              "Id": 3,
              "Name": null,
              "UnitTypeId": "G000UU8023", // смотритель.
              "SquadLinePosition": 0,
              "SquadFlankPosition": 0,
              "Level": 3,
              "Experience": 0,
              "HitPoints": 120,
              "IsDead": false
            },
            {
              "Id": 5,
              "Name": null,
              "UnitTypeId": "G000UU8015", // кентавр-латник.
              "SquadLinePosition": 1,
              "SquadFlankPosition": 1,
              "Level": 20,
              "Experience": 0,
              "HitPoints": 418,
              "IsDead": false
            },
          ]
        }
      ]
    },
    {
      "Id": 2,
      "IsComputer": true,
      "Squads": [
        {
          "Units": [
            {
              "Id": 9,
              "Name": null,
              "UnitTypeId": "G000UU6104", // жирный бес.
              "SquadLinePosition": 1,
              "SquadFlankPosition": 2,
              "Level": 1,
              "Experience": 0,
              "HitPoints": 100,
              "IsDead": false
            },
            {
              "Id": 10,
              "Name": null,
              "UnitTypeId": "G000UU6104", // жирный бес.
              "SquadLinePosition": 1,
              "SquadFlankPosition": 1,
              "Level": 10,
              "Experience": 0,
              "HitPoints": 190,
              "IsDead": false
            },
            {
              "Id": 11,
              "Name": null,
              "UnitTypeId": "G000UU6104", // жирный бес.
              "SquadLinePosition": 1,
              "SquadFlankPosition": 0,
              "Level": 1,
              "Experience": 0,
              "HitPoints": 100,
              "IsDead": false
            }
          ]
        }
      ]
    }
  ]
}