{
  "SagaName": "Drain life and drain life overflow",
  "SagaDescription": "Debug units with attack type: drain life, drain life overflow",
  "GameType": 0,
  "MissionType": 1,
  "TurnNumber": 1,
  "DifficultyLevel": 2,
  "Players": [
    {
      "Id": 1,
      "IsComputer": false,
      "Race": 0,
      "Squads": [
        {
          "Units": [
            {
              "Id": 2,
              "Name": null,
              "UnitTypeId": "G000UU0083", // вампир.
              "SquadLinePosition": 2,
              "SquadFlankPosition": 2,
              "Level": 4,
              "Experience": 0,
              "HitPoints": 185,
              "IsDead": false
            },
            {
              "Id": 5,
              "Name": null,
              "UnitTypeId": "G000UU0175", // древний вампир.
              "SquadLinePosition": 2,
              "SquadFlankPosition": 0,
              "Level": 5,
              "Experience": 0,
              "HitPoints": 210,
              "IsDead": false
            }
          ]
        }
      ]
    },
    {
      "Id": 2,
      "IsComputer": true,
      "Race": 3,
      "Squads": [
        {
          "Units": [
            {
              "Id": 9,
              "Name": null,
              "UnitTypeId": "G000UU0040", // почтенный воин.
              "SquadLinePosition": 2,
              "SquadFlankPosition": 0,
              "Level": 4,
              "Experience": 0,
              "HitPoints": 275,
              "IsDead": false
            },
            {
              "Id": 10,
              "Name": null,
              "UnitTypeId": "G000UU0040", // почтенный воин.
              "SquadLinePosition": 2,
              "SquadFlankPosition": 2,
              "Level": 4,
              "Experience": 0,
              "HitPoints": 275,
              "IsDead": false
            },
            {
              "Id": 11,
              "Name": null,
              "UnitTypeId": "G000UU0040", // почтенный воин.
              "SquadLinePosition": 1,
              "SquadFlankPosition": 0,
              "Level": 4,
              "Experience": 0,
              "HitPoints": 275,
              "IsDead": false
            },
            {
              "Id": 12,
              "Name": null,
              "UnitTypeId": "G000UU0040", // почтенный воин.
              "SquadLinePosition": 1,
              "SquadFlankPosition": 1,
              "Level": 4,
              "Experience": 0,
              "HitPoints": 275,
              "IsDead": false
            },
            {
              "Id": 13,
              "Name": null,
              "UnitTypeId": "G000UU0040", // почтенный воин.
              "SquadLinePosition": 1,
              "SquadFlankPosition": 2,
              "Level": 4,
              "Experience": 0,
              "HitPoints": 275,
              "IsDead": false
            }
          ]
        }
      ]
    }
  ]
}